__init__.py
testla_screenplay_playwright/__init__.py
testla_screenplay_playwright/api/__init__.py
testla_screenplay_playwright/api/types.py
testla_screenplay_playwright/api/abilities/__init__.py
testla_screenplay_playwright/api/abilities/use_api.py
testla_screenplay_playwright/api/actions/__init__.py
testla_screenplay_playwright/api/actions/abstract_request.py
testla_screenplay_playwright/api/actions/delete.py
testla_screenplay_playwright/api/actions/get.py
testla_screenplay_playwright/api/actions/head.py
testla_screenplay_playwright/api/actions/patch.py
testla_screenplay_playwright/api/actions/post.py
testla_screenplay_playwright/api/actions/put.py
testla_screenplay_playwright/api/questions/__init__.py
testla_screenplay_playwright/api/questions/response.py
testla_screenplay_playwright/shared/__init__.py
testla_screenplay_playwright/shared/actions/__init__.py
testla_screenplay_playwright/shared/actions/sleep.py
testla_screenplay_playwright/web/__init__.py
testla_screenplay_playwright/web/types.py
testla_screenplay_playwright/web/utils.py
testla_screenplay_playwright/web/abilities/__init__.py
testla_screenplay_playwright/web/abilities/browse_the_web.py
testla_screenplay_playwright/web/actions/__init__.py
testla_screenplay_playwright/web/actions/add.py
testla_screenplay_playwright/web/actions/check.py
testla_screenplay_playwright/web/actions/clear.py
testla_screenplay_playwright/web/actions/click.py
testla_screenplay_playwright/web/actions/double_click.py
testla_screenplay_playwright/web/actions/drag_and_drop.py
testla_screenplay_playwright/web/actions/fill.py
testla_screenplay_playwright/web/actions/get.py
testla_screenplay_playwright/web/actions/hover.py
testla_screenplay_playwright/web/actions/navigate.py
testla_screenplay_playwright/web/actions/press.py
testla_screenplay_playwright/web/actions/remove.py
testla_screenplay_playwright/web/actions/select.py
testla_screenplay_playwright/web/actions/set.py
testla_screenplay_playwright/web/actions/type.py
testla_screenplay_playwright-1.0.0.dist-info/LICENSE
testla_screenplay_playwright-1.0.0.dist-info/METADATA
testla_screenplay_playwright-1.0.0.dist-info/WHEEL
testla_screenplay_playwright-1.0.0.dist-info/top_level.txt
testla_screenplay_playwright-1.0.0.dist-info/RECORD
