Metadata-Version: 2.1
Name: testla-screenplay-playwright
Version: 1.0.0
Summary: Testla Screenplay Playwright Package
Author-email: Oliver Nguyen <oliver.nguyen@prosiebensat1.com>, Patrick Döring <patrick.doering@prosiebensat1.com>
License: MIT License
Project-URL: Homepage, https://github.com/testla-project/testla-screenplay-core-py
Project-URL: Bug Tracker, https://github.com/testla-project/testla-screenplay-core-py/issues
Classifier: Programming Language :: Python :: 3
Classifier: License :: OSI Approved :: MIT License
Classifier: Operating System :: OS Independent
Requires-Python: >=3.7
License-File: LICENSE
Requires-Dist: testla-screenplay
